curl_cffi/__init__.py
curl_cffi/__version__.py
curl_cffi/_asyncio_selector.py
curl_cffi/_wrapper.abi3.so
curl_cffi/aio.py
curl_cffi/cli.py
curl_cffi/const.py
curl_cffi/curl.py
curl_cffi/py.typed
curl_cffi/utils.py
curl_cffi/requests/__init__.py
curl_cffi/requests/cookies.py
curl_cffi/requests/errors.py
curl_cffi/requests/exceptions.py
curl_cffi/requests/headers.py
curl_cffi/requests/impersonate.py
curl_cffi/requests/models.py
curl_cffi/requests/session.py
curl_cffi/requests/utils.py
curl_cffi/requests/websockets.py
curl_cffi_patch-0.15.1.dist-info/METADATA
curl_cffi_patch-0.15.1.dist-info/WHEEL
curl_cffi_patch-0.15.1.dist-info/entry_points.txt
curl_cffi_patch-0.15.1.dist-info/top_level.txt
curl_cffi_patch-0.15.1.dist-info/RECORD
curl_cffi_patch-0.15.1.dist-info/licenses/LICENSE
