Metadata-Version: 2.4
Name: curl_cffi_patch
Version: 0.15.1
Summary: libcurl ffi bindings for Python, with impersonation support.
Author-email: lexiforest <infinitesheldon@gmail.com>
License: MIT License
Project-URL: repository, https://github.com/Ehsan-U/curl-cffi-patch
Classifier: Development Status :: 4 - Beta
Classifier: Intended Audience :: Developers
Classifier: Programming Language :: Python :: 3
Classifier: Programming Language :: Python :: 3.10
Classifier: Programming Language :: Python :: 3.11
Classifier: Programming Language :: Python :: 3.12
Classifier: Programming Language :: Python :: 3.13
Classifier: Programming Language :: Python :: 3.14
Requires-Python: >=3.10
License-File: LICENSE
Requires-Dist: cffi>=1.12.0
Requires-Dist: certifi>=2024.2.2
Provides-Extra: extra
Requires-Dist: readability-lxml>=0.8.1; extra == "extra"
Requires-Dist: markdownify>=1.1.0; extra == "extra"
Requires-Dist: lxml_html_clean; extra == "extra"
Provides-Extra: dev
Requires-Dist: charset_normalizer<4.0,>=3.3.2; extra == "dev"
Requires-Dist: coverage<7.0,>=6.4.1; extra == "dev"
Requires-Dist: cryptography<43.0,>=42.0.5; extra == "dev"
Requires-Dist: httpx==0.23.1; extra == "dev"
Requires-Dist: mypy<2.0,>=1.9.0; extra == "dev"
Requires-Dist: pytest<9.0,>=8.1.1; extra == "dev"
Requires-Dist: pytest-asyncio<1.0,>=0.23.6; extra == "dev"
Requires-Dist: pytest-trio<1.0,>=0.8.0; extra == "dev"
Requires-Dist: ruff<1.0,>=0.3.5; extra == "dev"
Requires-Dist: trio<1.0,>=0.25.0; extra == "dev"
Requires-Dist: trustme<2.0,>=1.1.0; extra == "dev"
Requires-Dist: uvicorn<1.0,>=0.29.0; extra == "dev"
Requires-Dist: websockets>=14.0; extra == "dev"
Requires-Dist: typing_extensions; extra == "dev"
Provides-Extra: build
Requires-Dist: cibuildwheel; extra == "build"
Requires-Dist: wheel; extra == "build"
Provides-Extra: test
Requires-Dist: charset_normalizer<4.0,>=3.3.2; extra == "test"
Requires-Dist: cryptography<43.0,>=42.0.5; extra == "test"
Requires-Dist: fastapi<1.0,>=0.110.0; extra == "test"
Requires-Dist: httpx==0.23.1; extra == "test"
Requires-Dist: proxy.py<3.0,>=2.4.3; extra == "test"
Requires-Dist: pytest<9.0,>=8.1.1; extra == "test"
Requires-Dist: pytest-asyncio<1.0,>=0.23.6; extra == "test"
Requires-Dist: pytest-trio<1.0,>=0.8.0; extra == "test"
Requires-Dist: python-multipart<1.0,>=0.0.9; extra == "test"
Requires-Dist: trio<1.0,>=0.25.0; extra == "test"
Requires-Dist: trustme<2.0,>=1.1.0; extra == "test"
Requires-Dist: uvicorn<1.0,>=0.29.0; extra == "test"
Requires-Dist: websockets>=14.0; extra == "test"
Requires-Dist: typing_extensions; extra == "test"
Dynamic: license-file
